bundler.py
bundler.py-0.1.1.dist-info/entry_points.txt
bundler.py-0.1.1.dist-info/LICENSE
bundler.py-0.1.1.dist-info/WHEEL
bundler.py-0.1.1.dist-info/METADATA
bundler.py-0.1.1.dist-info/RECORD
