Metadata-Version: 2.1
Name: bundler.py
Version: 0.1.1
Summary: A simple tool for packing shippable virtualenvs
Home-page: https://github.com/DisruptiveLabs/bundler.py
License: GPL-3.0-or-later
Keywords: virtualenv,shippable,packaging
Author: Franklyn Tackitt
Author-email: frank@comanage.com
Requires-Python: >=3.10,<4.0
Classifier: License :: OSI Approved :: GNU General Public License v3 or later (GPLv3+)
Classifier: Programming Language :: Python :: 3
Classifier: Programming Language :: Python :: 3.10
Classifier: Topic :: Software Development
Classifier: Topic :: Software Development :: Testing
Classifier: Topic :: System :: Archiving :: Packaging
Project-URL: Documentation, https://github.com/DisruptiveLabs/bundler.py
Project-URL: Repository, https://github.com/DisruptiveLabs/bundler.py
